package com.ja.analytics.framework;

import com.ja.analytics.logevent.EventLog;
import com.ja.analytics.net.HttpCallBackListener;
import org.json.JSONObject;

public class EventLogSend
{
  private static final String TAG = EventLogSend.class.getName();
  private static boolean isSendOK;
  private static EventLogSend mDataHandle = new EventLogSend();
  
  public static Boolean getSendFlag()
  {
    return Boolean.valueOf(isSendOK);
  }
  
  public static EventLogSend getSingleton()
  {
    return mDataHandle;
  }
  
  /* Error */
  private void sendData(android.content.Context paramContext, org.json.JSONArray paramJSONArray)
  {
    // Byte code:
    //   0: aload_0
    //   1: monitorenter
    //   2: getstatic 20	com/ja/analytics/framework/EventLogSend:TAG	Ljava/lang/String;
    //   5: ldc 46
    //   7: invokestatic 52	com/ja/analytics/utils/LogUtil:logD	(Ljava/lang/String;Ljava/lang/String;)I
    //   10: pop
    //   11: new 54	org/json/JSONObject
    //   14: dup
    //   15: invokespecial 55	org/json/JSONObject:<init>	()V
    //   18: pop
    //   19: invokestatic 60	com/ja/analytics/logevent/EventLog:getSingleton	()Lcom/ja/analytics/logevent/EventLog;
    //   22: aload_1
    //   23: invokevirtual 64	com/ja/analytics/logevent/EventLog:getProtocolHeader	(Landroid/content/Context;)Lorg/json/JSONObject;
    //   26: astore 6
    //   28: aload 6
    //   30: ldc 66
    //   32: aload_2
    //   33: invokevirtual 70	org/json/JSONObject:put	(Ljava/lang/String;Ljava/lang/Object;)Lorg/json/JSONObject;
    //   36: pop
    //   37: aload_1
    //   38: ldc 72
    //   40: aload 6
    //   42: new 74	com/ja/analytics/framework/EventLogSend$1
    //   45: dup
    //   46: aload_0
    //   47: invokespecial 77	com/ja/analytics/framework/EventLogSend$1:<init>	(Lcom/ja/analytics/framework/EventLogSend;)V
    //   50: invokestatic 83	com/ja/analytics/net/HttpUtils:postEvent	(Landroid/content/Context;Ljava/lang/String;Lorg/json/JSONObject;Lcom/ja/analytics/net/HttpCallBackListener;)V
    //   53: aload_0
    //   54: monitorexit
    //   55: return
    //   56: astore 7
    //   58: aload 7
    //   60: invokevirtual 86	org/json/JSONException:printStackTrace	()V
    //   63: goto -26 -> 37
    //   66: astore_3
    //   67: aload_0
    //   68: monitorexit
    //   69: aload_3
    //   70: athrow
    //   71: astore 8
    //   73: aload 8
    //   75: invokestatic 90	com/ja/analytics/utils/LogUtil:logException	(Ljava/lang/Throwable;)I
    //   78: pop
    //   79: goto -26 -> 53
    // Local variable table:
    //   start	length	slot	name	signature
    //   0	82	0	this	EventLogSend
    //   0	82	1	paramContext	android.content.Context
    //   0	82	2	paramJSONArray	org.json.JSONArray
    //   66	4	3	localObject	Object
    //   26	15	6	localJSONObject	JSONObject
    //   56	3	7	localJSONException	org.json.JSONException
    //   71	3	8	localException	Exception
    // Exception table:
    //   from	to	target	type
    //   28	37	56	org/json/JSONException
    //   2	28	66	finally
    //   28	37	66	finally
    //   37	53	66	finally
    //   58	63	66	finally
    //   73	79	66	finally
    //   37	53	71	java/lang/Exception
  }
  
  public static void setSendFlag(Boolean paramBoolean)
  {
    isSendOK = paramBoolean.booleanValue();
  }
  
  /* Error */
  public void sendFiveEventLog(android.content.Context paramContext, org.json.JSONArray paramJSONArray)
  {
    // Byte code:
    //   0: aload_0
    //   1: monitorenter
    //   2: getstatic 20	com/ja/analytics/framework/EventLogSend:TAG	Ljava/lang/String;
    //   5: ldc 101
    //   7: invokestatic 52	com/ja/analytics/utils/LogUtil:logD	(Ljava/lang/String;Ljava/lang/String;)I
    //   10: pop
    //   11: aload_2
    //   12: ifnonnull +15 -> 27
    //   15: getstatic 20	com/ja/analytics/framework/EventLogSend:TAG	Ljava/lang/String;
    //   18: ldc 103
    //   20: invokestatic 52	com/ja/analytics/utils/LogUtil:logD	(Ljava/lang/String;Ljava/lang/String;)I
    //   23: pop
    //   24: aload_0
    //   25: monitorexit
    //   26: return
    //   27: aload_2
    //   28: invokevirtual 109	org/json/JSONArray:length	()I
    //   31: istore 6
    //   33: iload 6
    //   35: iconst_5
    //   36: idiv
    //   37: istore 7
    //   39: iload 6
    //   41: iconst_5
    //   42: irem
    //   43: istore 8
    //   45: iconst_0
    //   46: istore 9
    //   48: iconst_0
    //   49: istore 10
    //   51: getstatic 20	com/ja/analytics/framework/EventLogSend:TAG	Ljava/lang/String;
    //   54: new 111	java/lang/StringBuilder
    //   57: dup
    //   58: ldc 113
    //   60: invokespecial 116	java/lang/StringBuilder:<init>	(Ljava/lang/String;)V
    //   63: aload_2
    //   64: invokevirtual 109	org/json/JSONArray:length	()I
    //   67: invokevirtual 120	java/lang/StringBuilder:append	(I)Ljava/lang/StringBuilder;
    //   70: invokevirtual 123	java/lang/StringBuilder:toString	()Ljava/lang/String;
    //   73: invokestatic 52	com/ja/analytics/utils/LogUtil:logD	(Ljava/lang/String;Ljava/lang/String;)I
    //   76: pop
    //   77: iload 6
    //   79: iconst_5
    //   80: if_icmplt +552 -> 632
    //   83: iconst_0
    //   84: istore 27
    //   86: iload 27
    //   88: iload 7
    //   90: if_icmplt +154 -> 244
    //   93: ldc2_w 124
    //   96: invokestatic 131	java/lang/Thread:sleep	(J)V
    //   99: new 105	org/json/JSONArray
    //   102: dup
    //   103: invokespecial 132	org/json/JSONArray:<init>	()V
    //   106: astore 42
    //   108: iconst_0
    //   109: istore 43
    //   111: iload 9
    //   113: iload 8
    //   115: if_icmplt +388 -> 503
    //   118: getstatic 20	com/ja/analytics/framework/EventLogSend:TAG	Ljava/lang/String;
    //   121: new 111	java/lang/StringBuilder
    //   124: dup
    //   125: ldc 134
    //   127: invokespecial 116	java/lang/StringBuilder:<init>	(Ljava/lang/String;)V
    //   130: aload 42
    //   132: invokevirtual 109	org/json/JSONArray:length	()I
    //   135: invokevirtual 120	java/lang/StringBuilder:append	(I)Ljava/lang/StringBuilder;
    //   138: invokevirtual 123	java/lang/StringBuilder:toString	()Ljava/lang/String;
    //   141: invokestatic 52	com/ja/analytics/utils/LogUtil:logD	(Ljava/lang/String;Ljava/lang/String;)I
    //   144: pop
    //   145: aload 42
    //   147: invokevirtual 109	org/json/JSONArray:length	()I
    //   150: ifeq -126 -> 24
    //   153: aload_0
    //   154: aload_1
    //   155: aload 42
    //   157: invokespecial 136	com/ja/analytics/framework/EventLogSend:sendData	(Landroid/content/Context;Lorg/json/JSONArray;)V
    //   160: invokestatic 138	com/ja/analytics/framework/EventLogSend:getSendFlag	()Ljava/lang/Boolean;
    //   163: invokevirtual 96	java/lang/Boolean:booleanValue	()Z
    //   166: ifeq +61 -> 227
    //   169: new 105	org/json/JSONArray
    //   172: dup
    //   173: invokespecial 132	org/json/JSONArray:<init>	()V
    //   176: pop
    //   177: invokestatic 144	com/ja/analytics/db/EventTable:getIdIndexArray	()Lorg/json/JSONArray;
    //   180: astore 46
    //   182: getstatic 20	com/ja/analytics/framework/EventLogSend:TAG	Ljava/lang/String;
    //   185: new 111	java/lang/StringBuilder
    //   188: dup
    //   189: ldc 146
    //   191: invokespecial 116	java/lang/StringBuilder:<init>	(Ljava/lang/String;)V
    //   194: aload 46
    //   196: invokevirtual 109	org/json/JSONArray:length	()I
    //   199: invokevirtual 120	java/lang/StringBuilder:append	(I)Ljava/lang/StringBuilder;
    //   202: invokevirtual 123	java/lang/StringBuilder:toString	()Ljava/lang/String;
    //   205: invokestatic 52	com/ja/analytics/utils/LogUtil:logD	(Ljava/lang/String;Ljava/lang/String;)I
    //   208: pop
    //   209: aload 46
    //   211: invokevirtual 109	org/json/JSONArray:length	()I
    //   214: ifeq -190 -> 24
    //   217: iconst_m1
    //   218: istore 48
    //   220: iload 10
    //   222: istore 49
    //   224: goto +607 -> 831
    //   227: getstatic 20	com/ja/analytics/framework/EventLogSend:TAG	Ljava/lang/String;
    //   230: ldc 148
    //   232: invokestatic 52	com/ja/analytics/utils/LogUtil:logD	(Ljava/lang/String;Ljava/lang/String;)I
    //   235: pop
    //   236: goto -212 -> 24
    //   239: astore_3
    //   240: aload_0
    //   241: monitorexit
    //   242: aload_3
    //   243: athrow
    //   244: new 105	org/json/JSONArray
    //   247: dup
    //   248: invokespecial 132	org/json/JSONArray:<init>	()V
    //   251: astore 28
    //   253: iconst_0
    //   254: istore 29
    //   256: iload 29
    //   258: iconst_5
    //   259: if_icmplt +86 -> 345
    //   262: getstatic 20	com/ja/analytics/framework/EventLogSend:TAG	Ljava/lang/String;
    //   265: new 111	java/lang/StringBuilder
    //   268: dup
    //   269: ldc 150
    //   271: invokespecial 116	java/lang/StringBuilder:<init>	(Ljava/lang/String;)V
    //   274: iload 9
    //   276: invokevirtual 120	java/lang/StringBuilder:append	(I)Ljava/lang/StringBuilder;
    //   279: invokevirtual 123	java/lang/StringBuilder:toString	()Ljava/lang/String;
    //   282: invokestatic 52	com/ja/analytics/utils/LogUtil:logD	(Ljava/lang/String;Ljava/lang/String;)I
    //   285: pop
    //   286: aload_0
    //   287: aload_1
    //   288: aload 28
    //   290: invokespecial 136	com/ja/analytics/framework/EventLogSend:sendData	(Landroid/content/Context;Lorg/json/JSONArray;)V
    //   293: invokestatic 138	com/ja/analytics/framework/EventLogSend:getSendFlag	()Ljava/lang/Boolean;
    //   296: invokevirtual 96	java/lang/Boolean:booleanValue	()Z
    //   299: ifeq +40 -> 339
    //   302: new 105	org/json/JSONArray
    //   305: dup
    //   306: invokespecial 132	org/json/JSONArray:<init>	()V
    //   309: pop
    //   310: invokestatic 144	com/ja/analytics/db/EventTable:getIdIndexArray	()Lorg/json/JSONArray;
    //   313: astore 32
    //   315: aload 32
    //   317: invokevirtual 109	org/json/JSONArray:length	()I
    //   320: istore 33
    //   322: iload 33
    //   324: ifeq -231 -> 93
    //   327: iconst_m1
    //   328: istore 34
    //   330: iconst_0
    //   331: istore 35
    //   333: iload 35
    //   335: iconst_5
    //   336: if_icmplt +56 -> 392
    //   339: iinc 27 1
    //   342: goto -256 -> 86
    //   345: aload_2
    //   346: iload 9
    //   348: invokevirtual 154	org/json/JSONArray:getJSONObject	(I)Lorg/json/JSONObject;
    //   351: astore 59
    //   353: aload 28
    //   355: iload 29
    //   357: aload 59
    //   359: invokevirtual 157	org/json/JSONArray:put	(ILjava/lang/Object;)Lorg/json/JSONArray;
    //   362: pop
    //   363: iload 29
    //   365: iconst_5
    //   366: if_icmpge +6 -> 372
    //   369: iinc 9 1
    //   372: iinc 29 1
    //   375: goto -119 -> 256
    //   378: astore 57
    //   380: getstatic 20	com/ja/analytics/framework/EventLogSend:TAG	Ljava/lang/String;
    //   383: aload 57
    //   385: invokestatic 160	com/ja/analytics/utils/LogUtil:logException	(Ljava/lang/String;Ljava/lang/Throwable;)I
    //   388: pop
    //   389: goto -17 -> 372
    //   392: aload 32
    //   394: iload 10
    //   396: invokevirtual 164	org/json/JSONArray:getInt	(I)I
    //   399: istore 39
    //   401: iload 39
    //   403: istore 34
    //   405: iload 35
    //   407: iconst_5
    //   408: if_icmpge +6 -> 414
    //   411: iinc 10 1
    //   414: iload 34
    //   416: iconst_m1
    //   417: if_icmpeq +424 -> 841
    //   420: getstatic 20	com/ja/analytics/framework/EventLogSend:TAG	Ljava/lang/String;
    //   423: new 111	java/lang/StringBuilder
    //   426: dup
    //   427: ldc 166
    //   429: invokespecial 116	java/lang/StringBuilder:<init>	(Ljava/lang/String;)V
    //   432: iload 10
    //   434: invokevirtual 120	java/lang/StringBuilder:append	(I)Ljava/lang/StringBuilder;
    //   437: ldc 168
    //   439: invokevirtual 171	java/lang/StringBuilder:append	(Ljava/lang/String;)Ljava/lang/StringBuilder;
    //   442: iload 34
    //   444: invokevirtual 120	java/lang/StringBuilder:append	(I)Ljava/lang/StringBuilder;
    //   447: invokevirtual 123	java/lang/StringBuilder:toString	()Ljava/lang/String;
    //   450: invokestatic 52	com/ja/analytics/utils/LogUtil:logD	(Ljava/lang/String;Ljava/lang/String;)I
    //   453: pop
    //   454: aload_1
    //   455: iload 34
    //   457: invokestatic 176	java/lang/Integer:valueOf	(I)Ljava/lang/Integer;
    //   460: invokestatic 180	com/ja/analytics/db/EventTable:updateEventLogSendFlagItem	(Landroid/content/Context;Ljava/lang/Integer;)V
    //   463: aload_1
    //   464: iload 34
    //   466: invokestatic 184	com/ja/analytics/db/EventTable:deleteEventLogItem	(Landroid/content/Context;I)V
    //   469: iconst_m1
    //   470: istore 34
    //   472: goto +369 -> 841
    //   475: astore 36
    //   477: getstatic 20	com/ja/analytics/framework/EventLogSend:TAG	Ljava/lang/String;
    //   480: aload 36
    //   482: invokestatic 160	com/ja/analytics/utils/LogUtil:logException	(Ljava/lang/String;Ljava/lang/Throwable;)I
    //   485: pop
    //   486: goto -72 -> 414
    //   489: astore 40
    //   491: getstatic 20	com/ja/analytics/framework/EventLogSend:TAG	Ljava/lang/String;
    //   494: aload 40
    //   496: invokestatic 160	com/ja/analytics/utils/LogUtil:logException	(Ljava/lang/String;Ljava/lang/Throwable;)I
    //   499: pop
    //   500: goto -401 -> 99
    //   503: aload 42
    //   505: iload 43
    //   507: aload_2
    //   508: iload 9
    //   510: invokevirtual 154	org/json/JSONArray:getJSONObject	(I)Lorg/json/JSONObject;
    //   513: invokevirtual 157	org/json/JSONArray:put	(ILjava/lang/Object;)Lorg/json/JSONArray;
    //   516: pop
    //   517: getstatic 20	com/ja/analytics/framework/EventLogSend:TAG	Ljava/lang/String;
    //   520: new 111	java/lang/StringBuilder
    //   523: dup
    //   524: ldc 186
    //   526: invokespecial 116	java/lang/StringBuilder:<init>	(Ljava/lang/String;)V
    //   529: iload 9
    //   531: invokevirtual 120	java/lang/StringBuilder:append	(I)Ljava/lang/StringBuilder;
    //   534: ldc 188
    //   536: invokevirtual 171	java/lang/StringBuilder:append	(Ljava/lang/String;)Ljava/lang/StringBuilder;
    //   539: aload_2
    //   540: iload 9
    //   542: invokevirtual 154	org/json/JSONArray:getJSONObject	(I)Lorg/json/JSONObject;
    //   545: invokevirtual 191	java/lang/StringBuilder:append	(Ljava/lang/Object;)Ljava/lang/StringBuilder;
    //   548: invokevirtual 123	java/lang/StringBuilder:toString	()Ljava/lang/String;
    //   551: invokestatic 52	com/ja/analytics/utils/LogUtil:logD	(Ljava/lang/String;Ljava/lang/String;)I
    //   554: pop
    //   555: iinc 43 1
    //   558: iinc 9 1
    //   561: goto -450 -> 111
    //   564: astore 53
    //   566: getstatic 20	com/ja/analytics/framework/EventLogSend:TAG	Ljava/lang/String;
    //   569: aload 53
    //   571: invokestatic 160	com/ja/analytics/utils/LogUtil:logException	(Ljava/lang/String;Ljava/lang/Throwable;)I
    //   574: pop
    //   575: goto -20 -> 555
    //   578: aload 46
    //   580: iload 49
    //   582: invokevirtual 164	org/json/JSONArray:getInt	(I)I
    //   585: istore 52
    //   587: iload 52
    //   589: istore 48
    //   591: iload 48
    //   593: iconst_m1
    //   594: if_icmpeq +253 -> 847
    //   597: aload_1
    //   598: iload 48
    //   600: invokestatic 176	java/lang/Integer:valueOf	(I)Ljava/lang/Integer;
    //   603: invokestatic 180	com/ja/analytics/db/EventTable:updateEventLogSendFlagItem	(Landroid/content/Context;Ljava/lang/Integer;)V
    //   606: aload_1
    //   607: iload 48
    //   609: invokestatic 184	com/ja/analytics/db/EventTable:deleteEventLogItem	(Landroid/content/Context;I)V
    //   612: iconst_m1
    //   613: istore 48
    //   615: goto +232 -> 847
    //   618: astore 50
    //   620: getstatic 20	com/ja/analytics/framework/EventLogSend:TAG	Ljava/lang/String;
    //   623: aload 50
    //   625: invokestatic 160	com/ja/analytics/utils/LogUtil:logException	(Ljava/lang/String;Ljava/lang/Throwable;)I
    //   628: pop
    //   629: goto -38 -> 591
    //   632: new 105	org/json/JSONArray
    //   635: dup
    //   636: invokespecial 132	org/json/JSONArray:<init>	()V
    //   639: astore 12
    //   641: iconst_0
    //   642: istore 13
    //   644: iload 13
    //   646: iload 8
    //   648: if_icmplt +135 -> 783
    //   651: getstatic 20	com/ja/analytics/framework/EventLogSend:TAG	Ljava/lang/String;
    //   654: new 111	java/lang/StringBuilder
    //   657: dup
    //   658: ldc 134
    //   660: invokespecial 116	java/lang/StringBuilder:<init>	(Ljava/lang/String;)V
    //   663: aload 12
    //   665: invokevirtual 109	org/json/JSONArray:length	()I
    //   668: invokevirtual 120	java/lang/StringBuilder:append	(I)Ljava/lang/StringBuilder;
    //   671: invokevirtual 123	java/lang/StringBuilder:toString	()Ljava/lang/String;
    //   674: invokestatic 52	com/ja/analytics/utils/LogUtil:logD	(Ljava/lang/String;Ljava/lang/String;)I
    //   677: pop
    //   678: aload 12
    //   680: invokevirtual 109	org/json/JSONArray:length	()I
    //   683: ifeq -659 -> 24
    //   686: aload_0
    //   687: aload_1
    //   688: aload 12
    //   690: invokespecial 136	com/ja/analytics/framework/EventLogSend:sendData	(Landroid/content/Context;Lorg/json/JSONArray;)V
    //   693: invokestatic 138	com/ja/analytics/framework/EventLogSend:getSendFlag	()Ljava/lang/Boolean;
    //   696: invokevirtual 96	java/lang/Boolean:booleanValue	()Z
    //   699: ifeq -472 -> 227
    //   702: new 105	org/json/JSONArray
    //   705: dup
    //   706: invokespecial 132	org/json/JSONArray:<init>	()V
    //   709: pop
    //   710: invokestatic 144	com/ja/analytics/db/EventTable:getIdIndexArray	()Lorg/json/JSONArray;
    //   713: astore 16
    //   715: aload 16
    //   717: invokevirtual 109	org/json/JSONArray:length	()I
    //   720: istore 17
    //   722: iload 17
    //   724: ifeq -700 -> 24
    //   727: iconst_m1
    //   728: istore 18
    //   730: iconst_0
    //   731: istore 19
    //   733: iload 19
    //   735: iload 8
    //   737: if_icmpge -510 -> 227
    //   740: aload 16
    //   742: iload 19
    //   744: invokevirtual 164	org/json/JSONArray:getInt	(I)I
    //   747: istore 22
    //   749: iload 22
    //   751: istore 18
    //   753: iload 18
    //   755: iconst_m1
    //   756: if_icmpeq +21 -> 777
    //   759: aload_1
    //   760: iload 18
    //   762: invokestatic 176	java/lang/Integer:valueOf	(I)Ljava/lang/Integer;
    //   765: invokestatic 180	com/ja/analytics/db/EventTable:updateEventLogSendFlagItem	(Landroid/content/Context;Ljava/lang/Integer;)V
    //   768: aload_1
    //   769: iload 18
    //   771: invokestatic 184	com/ja/analytics/db/EventTable:deleteEventLogItem	(Landroid/content/Context;I)V
    //   774: iconst_m1
    //   775: istore 18
    //   777: iinc 19 1
    //   780: goto -47 -> 733
    //   783: aload 12
    //   785: iload 13
    //   787: aload_2
    //   788: iload 13
    //   790: invokevirtual 154	org/json/JSONArray:getJSONObject	(I)Lorg/json/JSONObject;
    //   793: invokevirtual 157	org/json/JSONArray:put	(ILjava/lang/Object;)Lorg/json/JSONArray;
    //   796: pop
    //   797: iinc 13 1
    //   800: goto -156 -> 644
    //   803: astore 24
    //   805: getstatic 20	com/ja/analytics/framework/EventLogSend:TAG	Ljava/lang/String;
    //   808: aload 24
    //   810: invokestatic 160	com/ja/analytics/utils/LogUtil:logException	(Ljava/lang/String;Ljava/lang/Throwable;)I
    //   813: pop
    //   814: goto -17 -> 797
    //   817: astore 20
    //   819: getstatic 20	com/ja/analytics/framework/EventLogSend:TAG	Ljava/lang/String;
    //   822: aload 20
    //   824: invokestatic 160	com/ja/analytics/utils/LogUtil:logException	(Ljava/lang/String;Ljava/lang/Throwable;)I
    //   827: pop
    //   828: goto -75 -> 753
    //   831: iload 49
    //   833: iload 8
    //   835: if_icmplt -257 -> 578
    //   838: goto -611 -> 227
    //   841: iinc 35 1
    //   844: goto -511 -> 333
    //   847: iinc 49 1
    //   850: goto -19 -> 831
    // Local variable table:
    //   start	length	slot	name	signature
    //   0	853	0	this	EventLogSend
    //   0	853	1	paramContext	android.content.Context
    //   0	853	2	paramJSONArray	org.json.JSONArray
    //   239	4	3	localObject	Object
    //   31	50	6	i	int
    //   37	54	7	j	int
    //   43	793	8	k	int
    //   46	513	9	m	int
    //   49	384	10	n	int
    //   639	145	12	localJSONArray1	org.json.JSONArray
    //   642	156	13	i1	int
    //   713	28	16	localJSONArray2	org.json.JSONArray
    //   720	3	17	i2	int
    //   728	48	18	i3	int
    //   731	47	19	i4	int
    //   817	6	20	localJSONException1	org.json.JSONException
    //   747	3	22	i5	int
    //   803	6	24	localJSONException2	org.json.JSONException
    //   84	256	27	i6	int
    //   251	103	28	localJSONArray3	org.json.JSONArray
    //   254	119	29	i7	int
    //   313	80	32	localJSONArray4	org.json.JSONArray
    //   320	3	33	i8	int
    //   328	143	34	i9	int
    //   331	511	35	i10	int
    //   475	6	36	localJSONException3	org.json.JSONException
    //   399	3	39	i11	int
    //   489	6	40	localInterruptedException	java.lang.InterruptedException
    //   106	398	42	localJSONArray5	org.json.JSONArray
    //   109	447	43	i12	int
    //   180	399	46	localJSONArray6	org.json.JSONArray
    //   218	396	48	i13	int
    //   222	626	49	i14	int
    //   618	6	50	localJSONException4	org.json.JSONException
    //   585	3	52	i15	int
    //   564	6	53	localJSONException5	org.json.JSONException
    //   378	6	57	localJSONException6	org.json.JSONException
    //   351	7	59	localJSONObject	JSONObject
    // Exception table:
    //   from	to	target	type
    //   2	11	239	finally
    //   15	24	239	finally
    //   27	39	239	finally
    //   51	77	239	finally
    //   93	99	239	finally
    //   99	108	239	finally
    //   118	217	239	finally
    //   227	236	239	finally
    //   244	253	239	finally
    //   262	322	239	finally
    //   345	363	239	finally
    //   380	389	239	finally
    //   392	401	239	finally
    //   420	469	239	finally
    //   477	486	239	finally
    //   491	500	239	finally
    //   503	555	239	finally
    //   566	575	239	finally
    //   578	587	239	finally
    //   597	612	239	finally
    //   620	629	239	finally
    //   632	641	239	finally
    //   651	722	239	finally
    //   740	749	239	finally
    //   759	774	239	finally
    //   783	797	239	finally
    //   805	814	239	finally
    //   819	828	239	finally
    //   345	363	378	org/json/JSONException
    //   392	401	475	org/json/JSONException
    //   93	99	489	java/lang/InterruptedException
    //   503	555	564	org/json/JSONException
    //   578	587	618	org/json/JSONException
    //   783	797	803	org/json/JSONException
    //   740	749	817	org/json/JSONException
  }
}


/* Location:           C:\Users\yepeng\Documents\classes-dex2jar.jar
 * Qualified Name:     com.ja.analytics.framework.EventLogSend
 * JD-Core Version:    0.7.0.1
 */